arpys/__init__.py
arpys/dataloaders.py
arpys/fit2d.py
arpys/postprocessing.py
arpys/utilities/__init__.py
arpys/utilities/constants.py
arpys/utilities/functions.py
arpys/utilities/kolormap.py
arpys/utilities/plotting.py
arpys/utilities/cmaps/hanin.dat
arpys/utilities/cmaps/kocean_red.dat
arpys/utilities/cmaps/mslice.dat
arpys/utilities/cmaps/ocean_k.dat
arpys/utilities/cmaps/ocean_k_tail.dat
arpys/utilities/cmaps/ocean_k_tail_rgb.dat
arpys/utilities/cmaps/ocean_r.dat
arpys/utilities/cmaps/ocean_red_tail.dat
arpys/utilities/cmaps/ocean_red_tail_rgb.dat
arpys/utilities/cmaps/rainbow_light.dat
arpys/utilities/cmaps/unknown.dat
arpys-1.0.0.dist-info/COPYING
arpys-1.0.0.dist-info/COPYING.LESSER
arpys-1.0.0.dist-info/LICENSE-3RD-PARTY.txt
arpys-1.0.0.dist-info/METADATA
arpys-1.0.0.dist-info/WHEEL
arpys-1.0.0.dist-info/top_level.txt
arpys-1.0.0.dist-info/RECORD
