Metadata-Version: 2.1
Name: arpys
Version: 1.0.0
Summary: Python tools and scripts for ARPES data analysis
Home-page: https://github.com/kuadrat/arpys.git
Author: Kevin Kramer
Author-email: kevin.kramer@uzh.ch
License: UNKNOWN
Platform: UNKNOWN
Classifier: Programming Language :: Python :: 3
Classifier: License :: OSI Approved :: GNU General Public License v3 or later (GPLv3+)
Classifier: Operating System :: OS Independent
Requires-Dist: cycler (>=0.10.0)
Requires-Dist: h5py (>=2.7.1)
Requires-Dist: igor2 (>=0.5.2)
Requires-Dist: matplotlib (>=2.1.0)
Requires-Dist: numpy (>=1.8.0)
Requires-Dist: scipy (>=0.19.1)
Requires-Dist: astropy (>=4.0.1)
